framework_detector/__init__.py
framework_detector/dockerfiles/__init__.py
framework_detector/dockerfiles/django.Dockerfile
framework_detector/dockerfiles/flask.Dockerfile
framework_detector/dockerfiles/springboot.Dockerfile
framework_detector/frameworks/__init__.py
framework_detector/frameworks/django.json
framework_detector/frameworks/example.json
framework_detector/frameworks/flask.json
framework_detector/frameworks/springboot.json
framework_detector/main.py
framework_detector-0.2.1.dist-info/WHEEL
framework_detector-0.2.1.dist-info/METADATA
framework_detector-0.2.1.dist-info/RECORD
