Metadata-Version: 2.1
Name: framework-detector
Version: 0.2.1
Summary: Detects which framework is in use in a project
Home-page: https://github.com/pbexe/framework-detector
Author: Miles Budden
Author-email: git@miles.so
Requires-Python: >=3.9,<4.0
Classifier: Programming Language :: Python :: 3
Classifier: Programming Language :: Python :: 3.9
Project-URL: Repository, https://github.com/pbexe/framework-detector
